{
  "$schema": "./node_modules/@biomejs/biome/configuration_schema.json",
  "vcs": {
    "enabled": true,
    "clientKind": "git",
    "useIgnoreFile": true
  },
  "extends": [
    "ultracite/biome/core",
    "ultracite/biome/react",
    "ultracite/biome/remix"
  ],
  "files": {
    "ignoreUnknown": false,
    "includes": [
      "src/**/*",
      "*.config.ts",
      "!src/*.gen.ts",
      "!turbo",
      "!src/lib/components/ui/**/*",
      "!**/*.css",
      "!*.d.ts",
      "!stats.html",
      "!test-results/*.json"
    ]
  },
  "formatter": {
    "enabled": true,
    "indentStyle": "space"
  },
  "linter": {
    "enabled": true,
    "rules": {
      "recommended": true,
      "correctness": {
        "useImageSize": "off"
      },
      "style": {
        "useConsistentTypeDefinitions": "off",
        "useConsistentArrayType": {
          "level": "error",
          "options": {
            "syntax": "generic"
          }
        },
        "useFilenamingConvention": {
          "level": "error",
          "options": {
            "filenameCases": ["kebab-case"]
          }
        }
      }
    }
  },
  "javascript": {
    "formatter": {
      "quoteStyle": "single"
    }
  },
  "overrides": [
    {
      "includes": ["src/lib/pages/**/index.tsx", "src/*.ts", "*.ts"],
      "linter": {
        "rules": {
          "style": {
            "noDefaultExport": "off"
          }
        }
      }
    },
    {
      "includes": ["src/lib/components/**/*", "src/lib/hooks/**/*"],
      "linter": {
        "rules": {
          "style": {
            "useFilenamingConvention": "off"
          }
        }
      }
    },
    {
      "includes": ["src/lib/services/**/*"],
      "linter": {
        "rules": {
          "style": {
            "useFilenamingConvention": "off"
          }
        }
      }
    },
    {
      "includes": ["src/lib/components/pagination/index.ts"],
      "linter": {
        "rules": {
          "performance": {
            "noBarrelFile": "off"
          }
        }
      }
    },
    {
      "includes": ["src/lib/components/media/index.ts"],
      "linter": {
        "rules": {
          "performance": {
            "noBarrelFile": "off"
          }
        }
      }
    },
    {
      "includes": ["**/*.test.ts", "**/*.test.tsx"],
      "linter": {
        "rules": {
          "performance": {
            "useTopLevelRegex": "off",
            "noNamespaceImport": "off"
          },
          "style": {
            "useConsistentArrayType": "off",
            "noNonNullAssertion": "off"
          },
          "suspicious": {
            "useAwait": "off"
          }
        }
      }
    },
    {
      "includes": ["src/lib/components/kudos/send-modal/index.ts"],
      "linter": {
        "rules": {
          "performance": {
            "noBarrelFile": "off"
          }
        }
      }
    },
    {
      "includes": ["src/lib/components/reward/index.ts"],
      "linter": {
        "rules": {
          "performance": {
            "noBarrelFile": "off"
          }
        }
      }
    },
    {
      "includes": ["src/lib/types/index.ts"],
      "linter": {
        "rules": {
          "performance": {
            "noBarrelFile": "off"
          }
        }
      }
    }
  ],
  "assist": {
    "enabled": true,
    "actions": {
      "source": {
        "organizeImports": {
          "level": "on",
          "options": {
            "groups": [
              [":URL:", ":NODE:", ":PACKAGE:"],
              ":BLANK_LINE:",
              [":ALIAS:"],
              ":BLANK_LINE:",
              [":PATH:"]
            ]
          }
        }
      }
    }
  }
}
